LICENSE
setup.py
django_xmail_ritual.egg-info/PKG-INFO
django_xmail_ritual.egg-info/SOURCES.txt
django_xmail_ritual.egg-info/dependency_links.txt
django_xmail_ritual.egg-info/requires.txt
django_xmail_ritual.egg-info/top_level.txt
grimoire/django/xmail/__init__.py
grimoire/django/xmail/admin.py
grimoire/django/xmail/apps.py
grimoire/django/xmail/backends.py
grimoire/django/xmail/models.py
grimoire/django/xmail/settings.py
grimoire/django/xmail/locale/es/LC_MESSAGES/django.mo
grimoire/django/xmail/locale/es/LC_MESSAGES/django.po
grimoire/django/xmail/management/__init__.py
grimoire/django/xmail/management/commands/__init__.py
grimoire/django/xmail/management/commands/send_mails.py
grimoire/django/xmail/migrations/0001_initial.py
grimoire/django/xmail/migrations/0002_auto_20150419_2120.py
grimoire/django/xmail/migrations/0003_auto_20200319_0009.py
grimoire/django/xmail/migrations/0004_alter_asyncemailentry_id.py
grimoire/django/xmail/migrations/__init__.py