Metadata-Version: 2.1
Name: django-xmail-ritual
Version: 1.1.2
Summary: The xmail library is a mail dispatching library for Django 2.2 or greater. Mails are sent asynchronously by a management command
Home-page: https://github.com/luismasuelli/django-xmail-ritual
Author: Luis y Anita
Author-email: luismasuelli@hotmail.com
License: LGPL
License-File: LICENSE
